strobopy/__init__.py
strobopy/cli.py
strobopy/denoise.py
strobopy/fitting.py
strobopy/get_dm3.py
strobopy/load_dm3.py
strobopy/skeleton.py
strobopy/strobopy.py
strobopy-0.1.0.dist-info/LICENSE.txt
strobopy-0.1.0.dist-info/METADATA
strobopy-0.1.0.dist-info/WHEEL
strobopy-0.1.0.dist-info/top_level.txt
strobopy-0.1.0.dist-info/RECORD
