Metadata-Version: 2.1
Name: strobopy
Version: 0.1.0
Summary: Analysis package for ultrafast stroboscopic TEM data
Home-page: UNKNOWN
Author: 
Author-email: kbschliep@gmail.com
Maintainer: 
Maintainer-email: kbschliep@gmail.com
License: mit
Keywords: TEM,stroboscopic,microscopy
Platform: UNKNOWN
Classifier: Development Status :: 4 - Beta
Classifier: Intended Audience :: End Users/Desktop
Classifier: Natural Language :: English
Classifier: License :: OSI Approved :: MIT License
Classifier: Programming Language :: Python :: 3.5
Classifier: Programming Language :: Python :: 3.6
